[
 {
  "行政區別": "總計",
  "親民黨": "63,132",
  "國民黨": "529,749",
  "民進黨": "718,260"
 },
 {
  "行政區別": "桃園區",
  "親民黨": "12,661",
  "國民黨": "102,460",
  "民進黨": "146,904"
 },
 {
  "行政區別": "中壢區",
  "親民黨": "11,902",
  "國民黨": "107,499",
  "民進黨": "126,600"
 },
 {
  "行政區別": "大溪區",
  "親民黨": "2,393",
  "國民黨": "21,126",
  "民進黨": "32,801"
 },
 {
  "行政區別": "楊梅區",
  "親民黨": "4,906",
  "國民黨": "42,840",
  "民進黨": "51,449"
 },
 {
  "行政區別": "蘆竹區",
  "親民黨": "4,593",
  "國民黨": "33,227",
  "民進黨": "55,967"
 },
 {
  "行政區別": "大園區",
  "親民黨": "2,594",
  "國民黨": "18,096",
  "民進黨": "33,375"
 },
 {
  "行政區別": "龜山區",
  "親民黨": "4,810",
  "國民黨": "35,968",
  "民進黨": "54,130"
 },
 {
  "行政區別": "八德區",
  "親民黨": "5,630",
  "國民黨": "50,043",
  "民進黨": "64,446"
 },
 {
  "行政區別": "龍潭區",
  "親民黨": "3,468",
  "國民黨": "34,250",
  "民進黨": "35,605"
 },
 {
  "行政區別": "平鎮區",
  "親民黨": "6,637",
  "國民黨": "57,200",
  "民進黨": "71,172"
 },
 {
  "行政區別": "新屋區",
  "親民黨": "1,392",
  "國民黨": "10,891",
  "民進黨": "18,437"
 },
 {
  "行政區別": "觀音區",
  "親民黨": "1,913",
  "國民黨": "12,106",
  "民進黨": "25,336"
 },
 {
  "行政區別": "復興區",
  "親民黨": "233",
  "國民黨": "4,043",
  "民進黨": "2,038"
 }
]